whyqd/VERSION
whyqd/__init__.py
whyqd/__main__.py
whyqd/config/__init__.py
whyqd/config/ray_init.py
whyqd/config/settings.py
whyqd/core/__init__.py
whyqd/core/base.py
whyqd/core/crosswalk.py
whyqd/core/datasource.py
whyqd/core/schema.py
whyqd/core/transform.py
whyqd/crosswalk/__init__.py
whyqd/crosswalk/actions/__init__.py
whyqd/crosswalk/actions/calculate.py
whyqd/crosswalk/actions/categorise.py
whyqd/crosswalk/actions/collate.py
whyqd/crosswalk/actions/deblank.py
whyqd/crosswalk/actions/dedupe.py
whyqd/crosswalk/actions/delete_rows.py
whyqd/crosswalk/actions/new.py
whyqd/crosswalk/actions/pivot_categories.py
whyqd/crosswalk/actions/pivot_longer.py
whyqd/crosswalk/actions/rename.py
whyqd/crosswalk/actions/select.py
whyqd/crosswalk/actions/select_newest.py
whyqd/crosswalk/actions/select_oldest.py
whyqd/crosswalk/actions/separate.py
whyqd/crosswalk/actions/unite.py
whyqd/crosswalk/base/__init__.py
whyqd/crosswalk/base/action_base.py
whyqd/crosswalk/base/category_base.py
whyqd/crosswalk/base/morph_base.py
whyqd/crud/__init__.py
whyqd/crud/action.py
whyqd/crud/base.py
whyqd/crud/field.py
whyqd/dtypes/__init__.py
whyqd/dtypes/field.py
whyqd/dtypes/mime.py
whyqd/dtypes/status.py
whyqd/models/__init__.py
whyqd/models/action_category.py
whyqd/models/action_morph.py
whyqd/models/action_schema.py
whyqd/models/actionscript.py
whyqd/models/category.py
whyqd/models/citation.py
whyqd/models/column.py
whyqd/models/constraints.py
whyqd/models/crosswalk.py
whyqd/models/datasource.py
whyqd/models/fields.py
whyqd/models/modifier.py
whyqd/models/schema.py
whyqd/models/transform.py
whyqd/models/version.py
whyqd/parsers/__init__.py
whyqd/parsers/action.py
whyqd/parsers/category.py
whyqd/parsers/core.py
whyqd/parsers/datasource.py
whyqd/parsers/morph.py
whyqd/parsers/script.py
whyqd-1.2.5.dist-info/LICENSE
whyqd-1.2.5.dist-info/METADATA
whyqd-1.2.5.dist-info/WHEEL
whyqd-1.2.5.dist-info/RECORD
