Metadata-Version: 2.3
Name: whyqd
Version: 1.2.5
Summary: data wrangling simplicity, complete audit transparency, and at speed
License: BSD-3-Clause
Keywords: python,data-science,pandas,open-data,open-science,data-analysis,data-wrangling,data-management,munging,crosswalks
Author: Gavin Chait
Author-email: gchait@whythawk.com
Requires-Python: >=3.9,<4.0
Classifier: Development Status :: 5 - Production/Stable
Classifier: Environment :: Console
Classifier: Intended Audience :: Science/Research
Classifier: License :: OSI Approved :: BSD License
Classifier: Operating System :: OS Independent
Classifier: Programming Language :: Python
Classifier: Programming Language :: Python :: 3
Classifier: Programming Language :: Python :: 3.9
Classifier: Programming Language :: Python :: 3.10
Classifier: Programming Language :: Python :: 3.11
Classifier: Programming Language :: Python :: 3.12
Classifier: Programming Language :: Python :: 3.13
Classifier: Topic :: Scientific/Engineering
Provides-Extra: docs
Requires-Dist: grpcio (>=1.59.3)
Requires-Dist: modin (>=0.25.1)
Requires-Dist: numpy (>=1.21.1)
Requires-Dist: openpyxl (>=3.0.7)
Requires-Dist: pandas (>=1.5.2)
Requires-Dist: pyarrow (>=11.0.0)
Requires-Dist: pydantic (>=1.8.2)
Requires-Dist: pydantic-settings (>=2.8.1,<3.0.0)
Requires-Dist: python-dotenv (>=1.0.0)
Requires-Dist: randomname (>=0.2.1)
Requires-Dist: ray (>=2.2.0)
Requires-Dist: setuptools (>=67.7.2)
Requires-Dist: tabulate (>=0.8.9)
Requires-Dist: xlrd (>=2.0.1)
Project-URL: Documentation, https://whyqd.readthedocs.io/
Project-URL: Homepage, https://whyqd.com
Project-URL: Repository, https://github.com/whythawk/whyqd/
